README.md
setup.py
mould/__init__.py
mould/_constants.py
mould/_executor.py
mould/_utils.py
mould/test.py
mould.egg-info/PKG-INFO
mould.egg-info/SOURCES.txt
mould.egg-info/dependency_links.txt
mould.egg-info/top_level.txt