Metadata-Version: 2.1
Name: mould
Version: 0.0.7
Summary: A minimalistic python templating library
Home-page: UNKNOWN
Author: Ramakrishnan H
License: MIT
Platform: UNKNOWN
